service_config.py
us_service_config-0.0.5.dist-info/METADATA
us_service_config-0.0.5.dist-info/WHEEL
us_service_config-0.0.5.dist-info/top_level.txt
us_service_config-0.0.5.dist-info/RECORD
