Metadata-Version: 2.1
Name: us-service-config
Version: 0.0.5
Summary: A service config for us services
Home-page: https://github.com/ukuspeed
Author: Ukuspeed
Author-email: info@ukuspeed.gmail.com
License: UNKNOWN
Platform: UNKNOWN
Classifier: Programming Language :: Python :: 3
Classifier: License :: OSI Approved :: MIT License
Classifier: Operating System :: OS Independent
Requires-Python: >=3.6
Requires-Dist: getconf
Requires-Dist: srvlookup
Requires-Dist: dnspython
